.coveragerc
.flake8
.gitignore
.pylintrc
LICENSE
MANIFEST.in
README.md
min_requirements.txt
pytest.ini
requirements.txt
setup.cfg
setup.py
test_requirements.txt
tox.ini
.github/workflows/ctest.yml
.github/workflows/run.yml
.github/workflows/tox.yml
examples/complex/README.md
examples/complex/mp1.yaml
examples/complex/mp2.yaml
examples/complex/sa.yaml
examples/complex/sensor.yaml
examples/complex/maps/data_packet.yaml
examples/complex/maps/metadata_base.yaml
examples/complex/maps/modular_platform_base.yaml
examples/complex/maps/modular_platform_variant_1.yaml
examples/complex/maps/modular_platform_variant_2.yaml
examples/complex/maps/sensor.yaml
examples/complex/maps/standalone.yaml
examples/complex/maps/temp_sensor.yaml
examples/full/README.md
examples/full/main.yaml
examples/full/map_simple_full.yaml
examples/minimal/CMakeLists.txt
examples/minimal/README.md
examples/minimal/all_outputs.yaml
examples/minimal/main.yaml
examples/minimal/my_minimal_map.yaml
examples/minimal/c_files/CMakeLists.txt
examples/minimal/c_files/mm_cc.h
examples/minimal/c_files/mm_meta.h
examples/minimal/c_files/mm_typedefs.h
examples/minimal/c_files/mm_typedefs_map_1.h
examples/minimal/c_files/mm_typedefs_type_1.h
examples/minimal/tests/CMakeLists.txt
examples/minimal/tests/minimal.c
examples/minimal/tests/minimal.cpp
examples/philip/README.md
examples/philip/adc.yaml
examples/philip/dac.yaml
examples/philip/gpio.yaml
examples/philip/i2c.yaml
examples/philip/main.yaml
examples/philip/map.yaml
examples/philip/pwm.yaml
examples/philip/rtc.yaml
examples/philip/spi.yaml
examples/philip/sys.yaml
examples/philip/tmr.yaml
examples/philip/uart.yaml
memory_map_manager/__init__.py
memory_map_manager/__main__.py
memory_map_manager/_version.py
memory_map_manager/exporter.py
memory_map_manager/importer.py
memory_map_manager/json_sem_hash.py
memory_map_manager/mmm_config_parser.py
memory_map_manager.egg-info/PKG-INFO
memory_map_manager.egg-info/SOURCES.txt
memory_map_manager.egg-info/dependency_links.txt
memory_map_manager.egg-info/entry_points.txt
memory_map_manager.egg-info/requires.txt
memory_map_manager.egg-info/top_level.txt
memory_map_manager/data/mm_gen_cfg.json
memory_map_manager/data/mm_map_cfg.json
memory_map_manager/templates/header_end.h.j2
