Metadata-Version: 2.1
Name: memory-map-manager
Version: 2.0.1
Summary: C code generator that unifies interfaces for memory maps
Home-page: https://github.com/riot-appstore/memory_map_manager
Author: Kevin Weiss
Author-email: kevin.weiss@haw-hamburg.de
License: MIT
Platform: any
Classifier: License :: OSI Approved :: MIT License
Classifier: Programming Language :: Python :: 3
Classifier: Programming Language :: Python :: 3 :: Only
Classifier: Programming Language :: Python :: 3.7
Classifier: Programming Language :: Python :: 3.8
Classifier: Programming Language :: Python :: 3.9
Classifier: Programming Language :: Python :: 3.10
Classifier: Operating System :: OS Independent
Classifier: Development Status :: 4 - Beta
Classifier: Intended Audience :: Developers
Classifier: Environment :: Console
Classifier: Topic :: Utilities
Requires-Python: >=3.7
